MANIFEST.in
setup.cfg
setup.py
setup_ext.py
tw2/__init__.py
tw2.util.html5shim.egg-info/PKG-INFO
tw2.util.html5shim.egg-info/SOURCES.txt
tw2.util.html5shim.egg-info/dependency_links.txt
tw2.util.html5shim.egg-info/entry_points.txt
tw2.util.html5shim.egg-info/namespace_packages.txt
tw2.util.html5shim.egg-info/not-zip-safe
tw2.util.html5shim.egg-info/requires.txt
tw2.util.html5shim.egg-info/top_level.txt
tw2/util/__init__.py
tw2/util/html5shim/__init__.py
tw2/util/html5shim/base.py
tw2/util/html5shim/resources.py
tw2/util/html5shim/version.py
tw2/util/html5shim/static/html5shim/pre3.5/html5shim.min.js
tw2/util/html5shim/templates/__init__.py
tw2/util/html5shim/templates/shim.html
tw2/util/html5shim/templates/shim.mak