Metadata-Version: 1.1
Name: tw2.util.html5shim
Version: 2.0.1
Summary: HTML5 Shim resource for TW2
Home-page: https://github.com/toscawidgets/tw2.util.html5shim
Author: Greg Jurman
Author-email: gdj2214@rit.edu
License: UNKNOWN
Keywords: toscawidgets.widgets,html5-shim
Platform: UNKNOWN
Classifier: Development Status :: 3 - Alpha
Classifier: Environment :: Web Environment
Classifier: Environment :: Web Environment :: ToscaWidgets
Classifier: Topic :: Software Development :: Libraries :: Python Modules
Classifier: Topic :: Software Development :: Widget Sets
Classifier: Intended Audience :: Developers
Classifier: Operating System :: OS Independent
Classifier: Programming Language :: Python
